submission_22_06_26_stock_chandla_motz/src/clock.sv
/**
 * Outputs a clock signal based on the given rollover signal.
 * The clock signal changes on every positive edge of the rollover signal.
 * On a positive edge of the reset signal, the clock is reset to high.
 *
 * @param i_roll_over rollover signal.
 * @param i_reset reset signal.
 * @param o_clk set to generated clock signal.
 **/
module clock( input  logic i_roll_over,
              input  logic i_reset,
              output logic o_clk );
  logic m_clk;

  // on positive edge of input clock or reset
  // either reset counter or assign next value
  always_ff @(posedge i_roll_over, posedge i_reset)
    begin
      if( i_reset == 1'b1 )
        begin
          m_clk <= 0;
        end
      else
        begin
          if( i_roll_over == 1'b1 )
            begin
              m_clk <= ~m_clk;
            end
        end
    end

  assign o_clk = m_clk;
endmodule

submission_22_06_26_stock_chandla_motz/src/clock_tb.sv
/**
 * k = 3
 * Testbench of the clock derived from a counter's rollover signal.
 * reset:    | 1 | 0 | 0 | 0 | 0 | 0 | 0 | 0 | 0 | 0 |  0 | ...
 * cycle     | 0 | 1 | 2 | 3 | 4 | 5 | 6 | 7 | 8 | 9 | 10 | ...
 * mod k     | 0 | 1 | 2 | 0 | 1 | 2 | 0 | 1 | 2 | 0 |  1 | ...
 * rollover: | 0 | 0 | 0 | 1 | 0 | 0 | 1 | 0 | 0 | 1 |  0 | ...
 * clock:    | 1 | 1 | 1 | 1 | 0 | 0 | 1 | 1 | 1 | 1 |  0 | ...
 **/
module clock_tb;
  logic l_reset;
  logic l_roll_over;
  logic l_clk;

  // reset
  initial
    begin
      l_reset <= 1;
      #3;
      l_reset <= 0;
    end

  clock dut( l_roll_over,
             l_reset,
             l_clk );

  initial begin
    $dumpfile("dump_clock.vcd");
    $dumpvars;
    
    l_roll_over = 1'b0;

    #5;
    l_roll_over = 1'b0;
    assert( l_clk === 1'b1 );
    
    #10;
    l_roll_over = 1'b0;
    assert( l_clk === 1'b1 );
    
    #10;
    l_roll_over = 1'b0;
    assert( l_clk === 1'b1 );
    
    #10;
    l_roll_over = 1'b1;
    #1;
    assert( l_clk === 1'b0 );
    
    #10;
    l_roll_over = 1'b0;
    assert( l_clk === 1'b0 );
    
    #10;
    l_roll_over = 1'b0;
    assert( l_clk === 1'b0 );
    
    #10;
    l_roll_over = 1'b0;
    assert( l_clk === 1'b0 );
    
    #10;
    l_roll_over = 1'b1;
    #1;
    assert( l_clk === 1'b1 );
    
    #10;
    l_roll_over = 1'b0;
    assert( l_clk === 1'b1 );
    
    #10;
    l_roll_over = 1'b0;
    assert( l_clk === 1'b1 );
    
    #10;
    l_roll_over = 1'b0;
    assert( l_clk === 1'b1 );
    
    #10;
    l_roll_over = 1'b1;
    #1;
    assert( l_clk === 1'b0 );
    
    #10;
    l_roll_over = 1'b0;
    assert( l_clk === 1'b0 );
    
    #10;
    l_roll_over = 1'b0;
    assert( l_clk === 1'b0 );
    
    #10;
    l_roll_over = 1'b0;
    assert( l_clk === 1'b0 );
    
    #10;
    l_roll_over = 1'b1;
    #1;
    assert( l_clk === 1'b1 );
    
    #10;
    l_roll_over = 1'b0;
    assert( l_clk === 1'b1 );
    
    #10;
    l_roll_over = 1'b1;
    #1;
    assert( l_clk === 1'b0 );
    
    #10;
    l_roll_over = 1'b0;
    #1;
    assert( l_clk === 1'b0 );
    
    #10;
    l_roll_over = 1'b0;
    l_reset = 1'b1;
    #1;
    l_reset = 1'b0;    
    #1;
    assert( l_clk === 1'b1 );
    

    #10;
    l_roll_over = 1'b0;
    #1;
    assert( l_clk === 1'b1 );

    #10;
    l_roll_over = 1'b1;
    #1;
    assert( l_clk === 1'b0 );

    #10;
    l_roll_over = 1'b0;
    #1;
    assert( l_clk === 1'b0 );

    #10;
    l_roll_over = 1'b0;
    #1;
    assert( l_clk === 1'b0 );

    #10;
    l_roll_over = 1'b0;
    #1;
    assert( l_clk === 1'b0 );

    #10;
    l_roll_over = 1'b1;
    #1;
    assert( l_clk === 1'b1 );

    #10;
    l_roll_over = 1'b0;
    #1;
    assert( l_clk === 1'b1 );

    #10;

    $finish;
  end
endmodule

submission_22_06_26_stock_chandla_motz/src/dump_clock.vcd
$date
	Fri Jun 24 13:04:41 2022
$end
$version
	Icarus Verilog
$end
$timescale
	1s
$end
$scope module clock_tb $end
$var wire 1 ! l_clk $end
$var reg 1 " l_reset $end
$var reg 1 # l_roll_over $end
$scope module dut $end
$var wire 1 " i_reset $end
$var wire 1 # i_roll_over $end
$var wire 1 ! o_clk $end
$var reg 1 $ m_clk $end
$upscope $end
$upscope $end
$enddefinitions $end
#0
$dumpvars
1$
0#
1"
1!
$end
#3
0"
#35
0!
0$
1#
#46
0#
#76
1!
1$
1#
#87
0#
#117
0!
0$
1#
#128
0#
#158
1!
1$
1#
#169
0#
#179
0!
0$
1#
#190
0#
#201
1!
1$
1"
#202
0"
#224
0!
0$
1#
#235
0#
#268
1!
1$
1#
#279
0#
