submission_22_06_19_stock_chandla_motz/src/xor_3.sv
module xor_3 ( input  logic i_in0,
                            i_in1,
                            i_in2,
               output logic o_res );

    assign o_res = (i_in0 ^ i_in1 ^ i_in2) && !(i_in0 && i_in1 && i_in2);

endmodule

submission_22_06_19_stock_chandla_motz/src/mux_2.sv
module mux_2 #(parameter N=64) ( input  logic [N-1:0] i_in0,
                                                      i_in1,
                                 input  logic         i_s,
                                 output logic [N-1:0] o_out );
              // true : false            
  assign o_out = i_s ? i_in1 : i_in0;
                       
endmodule

submission_22_06_12_stock_chandla_motz/src/mux_4.sv
module mux_4 #(parameter N=64) ( input  logic [N-1:0] i_in0,
                                                      i_in1,
                                                      i_in2,
                                                      i_in3,
                                 input  logic [1:0]   i_s,
                                 output logic [N-1:0] o_out );
                              
  logic [N-1:0] l_out_0;
  logic [N-1:0] l_out_1;
  
  mux_2 #(N) m_mux2_0( i_in0   , i_in1   , i_s[0:0] , l_out_0 );
  mux_2 #(N) m_mux2_1( i_in2   , i_in3   , i_s[0:0] , l_out_1 );
  mux_2 #(N) m_mux2_2( l_out_0 , l_out_1 , i_s[1:1] , o_out   );
                       
endmodule

submission_22_06_19_stock_chandla_motz/src/adder.sv
module adder #(parameter N=64) ( input  logic [N-1:0] i_a,
                                                      i_b,
                                 input  logic         i_carry_in,
                                 output logic [N-1:0] o_s,
                                 output logic         o_carry_out );
  /* verilator lint_off WIDTH */
  assign { o_carry_out, o_s } = i_a + i_b + i_carry_in;
                              
endmodule

submission_22_06_05_stock_chandla_motz/src/alu.sv
module alu #(parameter N=64) ( input  logic [N-1:0] i_a,
                                                    i_b,
                               input  logic [1:0]   i_alu_ctrl,
                               output logic [N-1:0] o_result,
                               output logic         o_carry_out );

  logic [N-1:0] l_adder, l_and, l_or, l_b;
  
  mux_2 #(N) m_mux2( i_b, ~i_b, i_alu_ctrl[0:0], l_b );
  adder #(N) a_1( i_a, l_b, i_alu_ctrl[0:0], l_adder, o_carry_out );
  
  
  assign l_and = i_a & i_b;
  assign l_or  = i_a | i_b;
  
  mux_4 #(N) m_mux4( l_adder, l_adder, l_and, l_or, i_alu_ctrl, o_result );

endmodule

submission_22_06_19_stock_chandla_motz/src/alu_nzcv.sv
module alu_nzcv #(parameter N=64) ( input  logic [N-1:0] i_a,
                                                         i_b,
                                    input  logic [1:0]   i_alu_ctrl,
                                    output logic [N-1:0] o_result,
                                    output logic [3:0]   o_nzcv );

    logic l_carry_out;

    alu #(N) m_alu( i_a, i_b, i_alu_ctrl, o_result, l_carry_out );

    // negative flag
    assign o_nzcv[3] = o_result[N-1:N-1];

    // zero flag
    assign o_nzcv[2] = !o_result;

    // carry flag
    assign o_nzcv[1] = (!i_alu_ctrl[1:1] & l_carry_out);


    // overflow flag
    logic l_xor_temp;
    xor_3 m_xor_3(i_b[N-1:N-1], i_a[N-1:N-1], i_alu_ctrl[0:0], l_xor_temp); // C
    assign o_nzcv[0] = (
        (!i_alu_ctrl[1:1]) & // A
        (o_result[N-1:N-1] ^ i_a[N-1:N-1]) & // B
        (!l_xor_temp) // C
    );

endmodule

submission_22_06_12_stock_chandla_motz/src/alu_nzcv_tb.sv
/*
 * Testbench ALU_NZCV
 */
module alu_nzcv_tb;
  logic [1:0]  l_op;
  logic [31:0] l_a,
               l_b,
               l_out;
  logic [3:0]  l_nzcv;

  alu_nzcv #(32) dut( l_a, l_b, l_op, l_out, l_nzcv );
  
  initial begin
    $dumpfile("dump_alu_nzcv_tb.vcd");
    $dumpvars;
    
    //
    // add
    //
    l_a  = 32'h0000_0000;
    l_b  = 32'h0000_0000;
    l_op = 2'b00;
    
    #10;
    assert( l_out === 32'h0000_0000);
    assert( l_nzcv === 4'b0100);

    l_a  = 32'h0000_0000;
    l_b  = 32'hffff_ffff;

    #10;
    assert( l_out === 32'hffff_ffff);
    assert( l_nzcv === 4'b1000);

    l_a  = 32'h0000_0001;
    l_b  = 32'hffff_ffff;

    #10;
    assert( l_out === 32'h0000_0000);
    assert( l_nzcv === 4'b0110);

    l_a  = 32'h0000_ffff;
    l_b  = 32'h0000_0001;

    #10;
    assert( l_out === 32'h0001_0000);
    assert( l_nzcv === 4'b0000);

    //
    // sub
    //
    l_op = 2'b01;
    
    l_a  = 32'h0000_0000;
    l_b  = 32'h0000_0000;

    #10;
    assert( l_out === 32'h0000_0000);
    assert( l_nzcv === 4'b0110);

    l_a  = 32'h0001_0000;
    l_b  = 32'h0000_0001;

    #10;
    assert( l_out === 32'h0000_ffff);
    assert( l_nzcv === 4'b0010);

    //
    // and
    //
    l_op = 2'b10;
    
    l_a  = 32'hffff_ffff;
    l_b  = 32'hffff_ffff;

    #10;
    assert( l_out === 32'hffff_ffff);
    assert( l_nzcv === 4'b1000);

    l_a  = 32'hffff_ffff;
    l_b  = 32'h7743_3477;

    #10;
    assert( l_out === 32'h7743_3477);
    assert( l_nzcv === 4'b0000);

    l_a  = 32'h0000_0000;
    l_b  = 32'hffff_ffff;

    #10;
    assert( l_out === 32'h0000_0000);
    assert( l_nzcv === 4'b0100);

    //
    // or
    //
    l_op = 2'b11;
    
    l_a  = 32'h0000_0000;
    l_b  = 32'hffff_ffff;

    #10;
    assert( l_out === 32'hffff_ffff);
    assert( l_nzcv === 4'b1000);

    $finish;
  end
endmodule

submission_22_06_12_stock_chandla_motz/src/dump_alu_nzcv_tb.vcd
$date
	Sun Jun 12 20:04:11 2022
$end
$version
	Icarus Verilog
$end
$timescale
	1s
$end
$scope module alu_nzcv_tb $end
$var wire 32 ! l_out [31:0] $end
$var wire 4 " l_nzcv [3:0] $end
$var reg 32 # l_a [31:0] $end
$var reg 32 $ l_b [31:0] $end
$var reg 2 % l_op [1:0] $end
$scope module dut $end
$var wire 32 & i_a [31:0] $end
$var wire 2 ' i_alu_ctrl [1:0] $end
$var wire 32 ( i_b [31:0] $end
$var wire 32 ) o_result [31:0] $end
$var wire 4 * o_nzcv [3:0] $end
$var wire 1 + l_xor_temp $end
$var wire 1 , l_carry_out $end
$scope module m_alu $end
$var wire 32 - i_a [31:0] $end
$var wire 2 . i_alu_ctrl [1:0] $end
$var wire 32 / i_b [31:0] $end
$var wire 32 0 l_and [31:0] $end
$var wire 32 1 l_or [31:0] $end
$var wire 32 2 o_result [31:0] $end
$var wire 1 , o_carry_out $end
$var wire 32 3 l_b [31:0] $end
$var wire 32 4 l_adder [31:0] $end
$scope module a_1 $end
$var wire 32 5 i_a [31:0] $end
$var wire 1 6 i_carry_in $end
$var wire 32 7 o_s [31:0] $end
$var wire 1 , o_carry_out $end
$var wire 32 8 i_b [31:0] $end
$upscope $end
$scope module m_mux2 $end
$var wire 32 9 i_in0 [31:0] $end
$var wire 32 : i_in1 [31:0] $end
$var wire 1 ; i_s $end
$var wire 32 < o_out [31:0] $end
$upscope $end
$scope module m_mux4 $end
$var wire 32 = i_in0 [31:0] $end
$var wire 32 > i_in1 [31:0] $end
$var wire 32 ? i_in2 [31:0] $end
$var wire 32 @ i_in3 [31:0] $end
$var wire 2 A i_s [1:0] $end
$var wire 32 B o_out [31:0] $end
$var wire 32 C l_out_1 [31:0] $end
$var wire 32 D l_out_0 [31:0] $end
$scope module m_mux2_0 $end
$var wire 32 E i_in0 [31:0] $end
$var wire 32 F i_in1 [31:0] $end
$var wire 1 G i_s $end
$var wire 32 H o_out [31:0] $end
$upscope $end
$scope module m_mux2_1 $end
$var wire 32 I i_in0 [31:0] $end
$var wire 32 J i_in1 [31:0] $end
$var wire 1 K i_s $end
$var wire 32 L o_out [31:0] $end
$upscope $end
$scope module m_mux2_2 $end
$var wire 32 M i_in0 [31:0] $end
$var wire 32 N i_in1 [31:0] $end
$var wire 1 O i_s $end
$var wire 32 P o_out [31:0] $end
$upscope $end
$upscope $end
$upscope $end
$scope module m_xor_3 $end
$var wire 1 Q i_in0 $end
$var wire 1 R i_in1 $end
$var wire 1 S i_in2 $end
$var wire 1 + o_res $end
$upscope $end
$upscope $end
$upscope $end
$enddefinitions $end
#0
$dumpvars
0S
0R
0Q
b0 P
0O
b0 N
b0 M
b0 L
0K
b0 J
b0 I
b0 H
0G
b0 F
b0 E
b0 D
b0 C
b0 B
b0 A
b0 @
b0 ?
b0 >
b0 =
b0 <
0;
b11111111111111111111111111111111 :
b0 9
b0 8
b0 7
06
b0 5
b0 4
b0 3
b0 2
b0 1
b0 0
b0 /
b0 .
b0 -
0,
0+
b100 *
b0 )
b0 (
b0 '
b0 &
b0 %
b0 $
b0 #
b100 "
b0 !
$end
#10
1+
b1000 "
b1000 *
b11111111111111111111111111111111 !
b11111111111111111111111111111111 )
b11111111111111111111111111111111 2
b11111111111111111111111111111111 B
b11111111111111111111111111111111 P
b11111111111111111111111111111111 D
b11111111111111111111111111111111 H
b11111111111111111111111111111111 M
b11111111111111111111111111111111 4
b11111111111111111111111111111111 7
b11111111111111111111111111111111 =
b11111111111111111111111111111111 >
b11111111111111111111111111111111 E
b11111111111111111111111111111111 F
1Q
b0 :
b11111111111111111111111111111111 1
b11111111111111111111111111111111 @
b11111111111111111111111111111111 J
b11111111111111111111111111111111 3
b11111111111111111111111111111111 8
b11111111111111111111111111111111 <
b11111111111111111111111111111111 $
b11111111111111111111111111111111 (
b11111111111111111111111111111111 /
b11111111111111111111111111111111 9
#20
b0 !
b0 )
b0 2
b0 B
b0 P
b1 C
b1 L
b1 N
b0 D
b0 H
b0 M
b110 "
b110 *
b1 0
b1 ?
b1 I
b0 4
b0 7
b0 =
b0 >
b0 E
b0 F
1,
b1 #
b1 &
b1 -
b1 5
#30
0+
b0 "
b0 *
b10000000000000000 !
b10000000000000000 )
b10000000000000000 2
b10000000000000000 B
b10000000000000000 P
0,
b10000000000000000 D
b10000000000000000 H
b10000000000000000 M
0Q
b11111111111111111111111111111110 :
b1 3
b1 8
b1 <
b1111111111111111 1
b1111111111111111 @
b1111111111111111 J
b10000000000000000 4
b10000000000000000 7
b10000000000000000 =
b10000000000000000 >
b10000000000000000 E
b10000000000000000 F
b1 $
b1 (
b1 /
b1 9
b1111111111111111 #
b1111111111111111 &
b1111111111111111 -
b1111111111111111 5
#40
b110 "
b110 *
1,
1+
b0 !
b0 )
b0 2
b0 B
b0 P
b0 D
b0 H
b0 M
b0 C
b0 L
b0 N
b11111111111111111111111111111111 :
b11111111111111111111111111111111 3
b11111111111111111111111111111111 8
b11111111111111111111111111111111 <
b0 0
b0 ?
b0 I
b0 1
b0 @
b0 J
b0 4
b0 7
b0 =
b0 >
b0 E
b0 F
1S
1;
16
1G
1K
b0 $
b0 (
b0 /
b0 9
b0 #
b0 &
b0 -
b0 5
b1 %
b1 '
b1 .
b1 A
#50
b10 "
b10 *
b1111111111111111 !
b1111111111111111 )
b1111111111111111 2
b1111111111111111 B
b1111111111111111 P
b11111111111111111111111111111110 3
b11111111111111111111111111111110 8
b11111111111111111111111111111110 <
b10000000000000001 C
b10000000000000001 L
b10000000000000001 N
b1111111111111111 D
b1111111111111111 H
b1111111111111111 M
b11111111111111111111111111111110 :
b10000000000000001 1
b10000000000000001 @
b10000000000000001 J
b1111111111111111 4
b1111111111111111 7
b1111111111111111 =
b1111111111111111 >
b1111111111111111 E
b1111111111111111 F
b1 $
b1 (
b1 /
b1 9
b10000000000000000 #
b10000000000000000 &
b10000000000000000 -
b10000000000000000 5
#60
0+
b1000 "
b1000 *
b11111111111111111111111111111111 3
b11111111111111111111111111111111 8
b11111111111111111111111111111111 <
b11111111111111111111111111111110 D
b11111111111111111111111111111110 H
b11111111111111111111111111111110 M
b11111111111111111111111111111111 C
b11111111111111111111111111111111 L
b11111111111111111111111111111111 N
b11111111111111111111111111111111 !
b11111111111111111111111111111111 )
b11111111111111111111111111111111 2
b11111111111111111111111111111111 B
b11111111111111111111111111111111 P
1Q
b0 :
1R
b11111111111111111111111111111111 0
b11111111111111111111111111111111 ?
b11111111111111111111111111111111 I
b11111111111111111111111111111111 1
b11111111111111111111111111111111 @
b11111111111111111111111111111111 J
b11111111111111111111111111111110 4
b11111111111111111111111111111110 7
b11111111111111111111111111111110 =
b11111111111111111111111111111110 >
b11111111111111111111111111111110 E
b11111111111111111111111111111110 F
0S
0;
06
0G
0K
1O
b11111111111111111111111111111111 $
b11111111111111111111111111111111 (
b11111111111111111111111111111111 /
b11111111111111111111111111111111 9
b11111111111111111111111111111111 #
b11111111111111111111111111111111 &
b11111111111111111111111111111111 -
b11111111111111111111111111111111 5
b10 %
b10 '
b10 .
b10 A
#70
1+
b0 "
b0 *
b1110111010000110011010001110111 !
b1110111010000110011010001110111 )
b1110111010000110011010001110111 2
b1110111010000110011010001110111 B
b1110111010000110011010001110111 P
b1110111010000110011010001110110 D
b1110111010000110011010001110110 H
b1110111010000110011010001110110 M
b1110111010000110011010001110111 C
b1110111010000110011010001110111 L
b1110111010000110011010001110111 N
b1110111010000110011010001110110 4
b1110111010000110011010001110110 7
b1110111010000110011010001110110 =
b1110111010000110011010001110110 >
b1110111010000110011010001110110 E
b1110111010000110011010001110110 F
0Q
b10001000101111001100101110001000 :
b1110111010000110011010001110111 0
b1110111010000110011010001110111 ?
b1110111010000110011010001110111 I
b1110111010000110011010001110111 3
b1110111010000110011010001110111 8
b1110111010000110011010001110111 <
b1110111010000110011010001110111 $
b1110111010000110011010001110111 (
b1110111010000110011010001110111 /
b1110111010000110011010001110111 9
#80
b100 "
b100 *
b0 !
b0 )
b0 2
b0 B
b0 P
b0 C
b0 L
b0 N
b11111111111111111111111111111111 D
b11111111111111111111111111111111 H
b11111111111111111111111111111111 M
1Q
b0 :
b11111111111111111111111111111111 3
b11111111111111111111111111111111 8
b11111111111111111111111111111111 <
0R
b0 0
b0 ?
b0 I
b11111111111111111111111111111111 4
b11111111111111111111111111111111 7
b11111111111111111111111111111111 =
b11111111111111111111111111111111 >
b11111111111111111111111111111111 E
b11111111111111111111111111111111 F
0,
b11111111111111111111111111111111 $
b11111111111111111111111111111111 (
b11111111111111111111111111111111 /
b11111111111111111111111111111111 9
b0 #
b0 &
b0 -
b0 5
#90
0+
b1 D
b1 H
b1 M
b1000 "
b1000 *
b11111111111111111111111111111111 !
b11111111111111111111111111111111 )
b11111111111111111111111111111111 2
b11111111111111111111111111111111 B
b11111111111111111111111111111111 P
b0 3
b0 8
b0 <
b1 4
b1 7
b1 =
b1 >
b1 E
b1 F
0,
b11111111111111111111111111111111 C
b11111111111111111111111111111111 L
b11111111111111111111111111111111 N
1S
1;
16
1G
1K
b11 %
b11 '
b11 .
b11 A
